aether_gestalt/__init__.py
aether_gestalt/gestalt.py
aether_gestalt-1.0.0.dist-info/licenses/LICENSE
aether_gestalt-1.0.0.dist-info/METADATA
aether_gestalt-1.0.0.dist-info/WHEEL
aether_gestalt-1.0.0.dist-info/top_level.txt
aether_gestalt-1.0.0.dist-info/RECORD
