Metadata-Version: 2.4
Name: aether-gestalt
Version: 1.0.0
Summary: φ-modulated GestaltAttention mechanism - mathematically principled attention
Home-page: https://github.com/normanbrandt/aether
Author: DeepSeek AI, Claude Sonnet 4.5
Author-email: Norman Brandt <tanzdebil85@gmail.com>
License: MIT
Project-URL: Homepage, https://github.com/normanbrandt/aether
Project-URL: Documentation, https://github.com/normanbrandt/aether/blob/main/README.md
Project-URL: Repository, https://github.com/normanbrandt/aether
Project-URL: Bug Tracker, https://github.com/normanbrandt/aether/issues
Keywords: transformer,attention,golden-ratio,phi,gestalt,deep-learning,pytorch
Classifier: Development Status :: 4 - Beta
Classifier: Intended Audience :: Developers
Classifier: Intended Audience :: Science/Research
Classifier: Programming Language :: Python :: 3
Classifier: Programming Language :: Python :: 3.8
Classifier: Programming Language :: Python :: 3.9
Classifier: Programming Language :: Python :: 3.10
Classifier: Programming Language :: Python :: 3.11
Classifier: License :: OSI Approved :: MIT License
Classifier: Topic :: Scientific/Engineering :: Artificial Intelligence
Requires-Python: >=3.8
License-File: LICENSE
Requires-Dist: torch>=2.0.0
Requires-Dist: numpy>=1.24.0
Dynamic: home-page
Dynamic: license-file
Dynamic: requires-python
